.coveragerc
.stestr.conf
.zuul.yaml
AUTHORS
CONTRIBUTING.rst
ChangeLog
HACKING.rst
LICENSE
README.rst
babel.cfg
bindep.txt
lower-constraints.txt
requirements.txt
setup.cfg
setup.py
test-requirements.txt
tox.ini
doc/requirements.txt
doc/source/conf.py
doc/source/index.rst
doc/source/admin/AMQP1.0.rst
doc/source/admin/drivers.rst
doc/source/admin/index.rst
doc/source/admin/kafka.rst
doc/source/admin/rabbit.rst
doc/source/configuration/conffixture.rst
doc/source/configuration/index.rst
doc/source/configuration/opts.rst
doc/source/contributor/contributing.rst
doc/source/contributor/driver-dev-guide.rst
doc/source/contributor/index.rst
doc/source/contributor/supported-messaging-drivers.rst
doc/source/reference/exceptions.rst
doc/source/reference/executors.rst
doc/source/reference/index.rst
doc/source/reference/notification_driver.rst
doc/source/reference/notification_listener.rst
doc/source/reference/notifier.rst
doc/source/reference/rpcclient.rst
doc/source/reference/serializer.rst
doc/source/reference/server.rst
doc/source/reference/target.rst
doc/source/reference/transport.rst
doc/source/user/FAQ.rst
doc/source/user/history.rst
doc/source/user/index.rst
etc/routing_notifier.yaml.sample
oslo_messaging/__init__.py
oslo_messaging/_utils.py
oslo_messaging/conffixture.py
oslo_messaging/dispatcher.py
oslo_messaging/exceptions.py
oslo_messaging/opts.py
oslo_messaging/serializer.py
oslo_messaging/server.py
oslo_messaging/target.py
oslo_messaging/transport.py
oslo_messaging/version.py
oslo_messaging/_drivers/__init__.py
oslo_messaging/_drivers/amqp.py
oslo_messaging/_drivers/amqpdriver.py
oslo_messaging/_drivers/base.py
oslo_messaging/_drivers/common.py
oslo_messaging/_drivers/impl_amqp1.py
oslo_messaging/_drivers/impl_fake.py
oslo_messaging/_drivers/impl_kafka.py
oslo_messaging/_drivers/impl_rabbit.py
oslo_messaging/_drivers/pool.py
oslo_messaging/_drivers/amqp1_driver/__init__.py
oslo_messaging/_drivers/amqp1_driver/addressing.py
wafec.oslo.messaging.egg-info/PKG-INFO
wafec.oslo.messaging.egg-info/SOURCES.txt
wafec.oslo.messaging.egg-info/dependency_links.txt
wafec.oslo.messaging.egg-info/pbr.json
wafec.oslo.messaging.egg-info/top_level.txt